fifo/__init__.py
pyfifo-1.0.0.dist-info/LICENSE
pyfifo-1.0.0.dist-info/METADATA
pyfifo-1.0.0.dist-info/WHEEL
pyfifo-1.0.0.dist-info/top_level.txt
pyfifo-1.0.0.dist-info/RECORD
